Metadata-Version: 1.1
Name: fit
Version: 0.4.1
Summary: FIT file I/O
Home-page: https://github.com/rembish/fit
Author: Aleksey Rembish
Author-email: alex@rembish.org
License: BSD
Platform: UNKNOWN
Classifier: Development Status :: 4 - Beta
Classifier: License :: OSI Approved :: BSD License
Classifier: Programming Language :: Python :: 2.7
